foldamers/__init__.py
foldamers/cg_model/__init__.py
foldamers/cg_model/cgmodel.py
foldamers/ensembles/__init__.py
foldamers/ensembles/cluster.py
foldamers/ensembles/ens_build.py
foldamers/parameters/__init__.py
foldamers/parameters/optimize.py
foldamers/parameters/reweight.py
foldamers/parameters/scan.py
foldamers/parameters/secondary_structure.py
foldamers/thermo/__init__.py
foldamers/thermo/calc.py
foldamers/thermo/util.py
foldamers/utilities/__init__.py
foldamers/utilities/iotools.py
foldamers/utilities/measure.py
foldamers/utilities/plot.py
foldamers/utilities/util.py
structure_library/__init__.py
foldamers-1.12.dist-info/LICENSE
foldamers-1.12.dist-info/METADATA
foldamers-1.12.dist-info/WHEEL
foldamers-1.12.dist-info/top_level.txt
foldamers-1.12.dist-info/RECORD
