Metadata-Version: 2.1
Name: foldamers
Version: 1.12
Summary: Package containing tools to model secondary structure formation in heteropolymers.
Home-page: https://github.com/shirtsgroup/foldamers
Author: Shirts research group
Author-email: michael.shirts@colorado.edu
License: MIT
Keywords: foldamers,coarse grained models,parameter re-weighting,oligomers
Platform: UNKNOWN
Classifier: License :: OSI Approved :: MIT License
Classifier: Programming Language :: Python
Classifier: Programming Language :: Python :: 3
Classifier: Programming Language :: Python :: 3.6
Classifier: Programming Language :: Python :: Implementation :: CPython
Classifier: Programming Language :: Python :: Implementation :: PyPy
Requires-Python: >=3.6.8
Requires-Dist: cg-openmm
Requires-Dist: pymbar
